{
  "frames": {
    "idle": { "frame": {"x":32,"y":32,"w":16,"h":32} },
    "run1": { "frame": {"x":32,"y":160,"w":16,"h":32} },
    "run2": { "frame": {"x":48,"y":160,"w":16,"h":32} },
    "run3": { "frame": {"x":64,"y":160,"w":16,"h":32} },
    "run4": { "frame": {"x":80,"y":160,"w":16,"h":32} },
    "jump1": { "frame": {"x":226,"y":32,"w":16,"h":32} },
    "jump2": { "frame": {"x":248,"y":32,"w":16,"h":32} },
    "jump3": { "frame": {"x":274,"y":32,"w":16,"h":32} },
    "jump4": { "frame": {"x":298,"y":32,"w":16,"h":32} },
    "climb1": { "frame": {"x":32,"y":190,"w":16,"h":32} },
    "climb2": { "frame": {"x":48,"y":190,"w":16,"h":32} },
    "climb3": { "frame": {"x":64,"y":190,"w":16,"h":32} },
    "climb4": { "frame": {"x":80,"y":190,"w":16,"h":32} }
  },
  "meta": {
    "image": "player.png",
    "size": {"w":448,"h":224},
    "scale": "1"
  }
}
